logiqaidstsyslogng.py
logiqaidstsyslogng-1.0.5.dist-info/LICENSE
logiqaidstsyslogng-1.0.5.dist-info/METADATA
logiqaidstsyslogng-1.0.5.dist-info/WHEEL
logiqaidstsyslogng-1.0.5.dist-info/top_level.txt
logiqaidstsyslogng-1.0.5.dist-info/RECORD
