Metadata-Version: 2.1
Name: logiqaidstsyslogng
Version: 1.0.5
Summary: Syslog-ng Python destination for LOGIQ.AI
Home-page: https://www.logiq.ai
Author: Ranjan Parthasarathy
Author-email: support@logiq.ai
License: UNKNOWN
Platform: UNKNOWN
Classifier: Programming Language :: Python :: 3
Classifier: License :: OSI Approved :: MIT License
Classifier: Operating System :: OS Independent
Requires-Python: >=2.7, !=3.0.*, !=3.1.*, !=3.2.*, <4
Requires-Dist: configparser
Requires-Dist: requests
Requires-Dist: urllib3
